odoo/addons/auth_api_key_server_env/README.rst
odoo/addons/auth_api_key_server_env/__init__.py
odoo/addons/auth_api_key_server_env/__manifest__.py
odoo/addons/auth_api_key_server_env/i18n/auth_api_key_server_env.pot
odoo/addons/auth_api_key_server_env/models/__init__.py
odoo/addons/auth_api_key_server_env/models/auth_api_key.py
odoo/addons/auth_api_key_server_env/readme/CONTRIBUTORS.rst
odoo/addons/auth_api_key_server_env/readme/DESCRIPTION.rst
odoo/addons/auth_api_key_server_env/static/description/icon.png
odoo/addons/auth_api_key_server_env/static/description/index.html
odoo/addons/auth_api_key_server_env/tests/__init__.py
odoo/addons/auth_api_key_server_env/tests/test_auth_api_key.py
odoo14_addon_auth_api_key_server_env-14.0.1.1.0.dist-info/METADATA
odoo14_addon_auth_api_key_server_env-14.0.1.1.0.dist-info/WHEEL
odoo14_addon_auth_api_key_server_env-14.0.1.1.0.dist-info/top_level.txt
odoo14_addon_auth_api_key_server_env-14.0.1.1.0.dist-info/RECORD
