Metadata-Version: 2.1
Name: odoo14-addon-auth-api-key-server-env
Version: 14.0.1.1.0
Summary: Configure api keys via server env. This can be very useful to avoid mixing your keys between your various environments when restoring databases. All you have to do is to add a new section to your configuration file according to the following convention:
Home-page: https://github.com/OCA/server-auth
Author: Camptocamp,Odoo Community Association (OCA)
Author-email: support@odoo-community.org
License: LGPL-3
Platform: UNKNOWN
Classifier: Programming Language :: Python
Classifier: Framework :: Odoo
Classifier: Framework :: Odoo :: 14.0
Classifier: License :: OSI Approved :: GNU Lesser General Public License v3 (LGPLv3)
Classifier: Development Status :: 5 - Production/Stable
Requires-Python: >=3.6
Requires-Dist: odoo14-addon-auth-api-key
Requires-Dist: odoo14-addon-server-environment
Requires-Dist: odoo (<14.1dev,>=14.0a)
